euchar/__init__.py
euchar/curve.py
euchar/display.py
euchar/filtrations.py
euchar/surface.py
euchar/utils.py
euchar/cppbinding/__init__.py
euchar/cppbinding/curve.cp37-win_amd64.pyd
euchar/cppbinding/surface.cp37-win_amd64.pyd
euchar/cppbinding/utils.cp37-win_amd64.pyd
euchar-0.1.6.dist-info/LICENSE
euchar-0.1.6.dist-info/METADATA
euchar-0.1.6.dist-info/WHEEL
euchar-0.1.6.dist-info/top_level.txt
euchar-0.1.6.dist-info/RECORD
