Metadata-Version: 2.1
Name: euchar
Version: 0.1.6
Summary: Euler characteristic of images and finite point sets.
Home-page: https://github.com/gbeltramo/euchar
Author: Gabriele Beltramo
Author-email: gabri.beltramo@gmail.com
License: MIT
Keywords: topology data analysis,euler characteristic,euler characteristic curve,euler characteristic surface
Platform: UNKNOWN
Classifier: Development Status :: 3 - Alpha
Classifier: Intended Audience :: Science/Research
Classifier: Intended Audience :: Education
Classifier: Topic :: Scientific/Engineering :: Mathematics
Classifier: License :: OSI Approved :: MIT License
Classifier: Programming Language :: Python :: 2.7
Classifier: Programming Language :: Python :: 3
Classifier: Programming Language :: Python :: 3.5
Classifier: Programming Language :: Python :: 3.6
Classifier: Programming Language :: Python :: 3.7
Requires-Python: >=2.7,!=3.1,!=3.2,!=3.3,!=3.4
Requires-Dist: numpy
Requires-Dist: matplotlib
Requires-Dist: scipy
Requires-Dist: scikit-learn
Requires-Dist: pybind11
